cg_simulator/__init__.py
cg_simulator/accordion/__init__.py
cg_simulator/accordion/core.py
cg_simulator/accordion/simulator.py
cg_simulator/cli.py
cg_simulator/core.py
cg_simulator-0.1.1.dist-info/entry_points.txt
cg_simulator-0.1.1.dist-info/WHEEL
cg_simulator-0.1.1.dist-info/METADATA
cg_simulator-0.1.1.dist-info/RECORD
